oligodimer/__init__.py
oligodimer/cmd/__init__.py
oligodimer/cmd/oligodimercli.py
oligodimer/core/__init__.py
oligodimer/core/multiplex.py
oligodimer/core/version.py
oligodimer/web/__init__.py
oligodimer/web/config.py
oligodimer/web/run.py
oligodimer/web/web_config_sample.json
oligodimer/web/static/favicon.ico
oligodimer/web/static/css/back-to-top.css
oligodimer/web/static/css/bootstrap-select.min.css
oligodimer/web/static/css/bootstrap.min.css
oligodimer/web/static/css/font-awesome.min.css
oligodimer/web/static/css/gh-fork-ribbon.ie.min.css
oligodimer/web/static/css/gh-fork-ribbon.min.css
oligodimer/web/static/css/style.css
oligodimer/web/static/css/validationEngine.jquery.css
oligodimer/web/static/fonts/FontAwesome.otf
oligodimer/web/static/fonts/fontawesome-webfont.eot
oligodimer/web/static/fonts/fontawesome-webfont.svg
oligodimer/web/static/fonts/fontawesome-webfont.ttf
oligodimer/web/static/fonts/fontawesome-webfont.woff
oligodimer/web/static/fonts/fontawesome-webfont.woff2
oligodimer/web/static/fonts/glyphicons-halflings-regular.eot
oligodimer/web/static/fonts/glyphicons-halflings-regular.svg
oligodimer/web/static/fonts/glyphicons-halflings-regular.ttf
oligodimer/web/static/fonts/glyphicons-halflings-regular.woff
oligodimer/web/static/fonts/glyphicons-halflings-regular.woff2
oligodimer/web/static/js/back-to-top.js
oligodimer/web/static/js/bootstrap-select.min.js
oligodimer/web/static/js/bootstrap.min.js
oligodimer/web/static/js/jquery.min.js
oligodimer/web/static/js/jquery.phoenix.min.js
oligodimer/web/static/js/jquery.validationEngine-en.js
oligodimer/web/static/js/jquery.validationEngine.min.js
oligodimer/web/static/js/oligodimer.js
oligodimer/web/templates/error.html
oligodimer/web/templates/index.html
oligodimer-1.0.1.dist-info/METADATA
oligodimer-1.0.1.dist-info/WHEEL
oligodimer-1.0.1.dist-info/entry_points.txt
oligodimer-1.0.1.dist-info/top_level.txt
oligodimer-1.0.1.dist-info/RECORD
