Metadata-Version: 2.1
Name: oligodimer
Version: 1.0.1
Summary: Detecting dimers among multiple oligo sequences
Home-page: https://github.com/billzt/OligoDimer
Author: Tao Zhu
Author-email: taozhu@mail.bnu.edu.cn
License: MIT
Keywords: dimer oligo bioinformatics PCR
Platform: UNKNOWN
Classifier: Intended Audience :: Science/Research
Classifier: License :: OSI Approved :: MIT License
Classifier: Operating System :: Unix
Classifier: Programming Language :: Python :: 3.6
Classifier: Topic :: Scientific/Engineering :: Bio-Informatics
Requires-Python: >=3.6
Requires-Dist: primer3-py
Requires-Dist: progressbar2
Requires-Dist: flask
Requires-Dist: python-dotenv
